{"createdAt":"2025-09-02T21:55:02.315Z","updatedAt":"2025-09-10T22:30:21.966Z","id":"n2dl4AfPiyRCVxpr","name":"FORMULARIO CONTACTO WEB EFICIENCIA","active":true,"isArchived":false,"nodes":[{"parameters":{"formTitle":"Contacto","formFields":{"values":[{"fieldLabel":"Nombre","placeholder":"Escriba su nombre completo","requiredField":true},{"fieldLabel":"Correo electr贸nico","fieldType":"email","placeholder":"tu@correo.com","requiredField":true},{"fieldLabel":"Tel茅fono","placeholder":"tu numero de telefono","requiredField":true},{"fieldLabel":"Mensaje","fieldType":"textarea","placeholder":"驴En que podemos ayudarte?","requiredField":true}]},"options":{"appendAttribution":false,"buttonLabel":"Enviar Mensaje","respondWithOptions":{"values":{"formSubmittedText":"Gracias por enviar tu mensaje, nos pondremos en contacto contigo en cuanto antes."}},"ignoreBots":true,"customCss":":root {\n  --font-family: 'Inter', sans-serif;\n  --font-weight-normal: 400;\n  --font-weight-bold: 600;\n  --font-size-body: 14px;\n  --font-size-label: 14px;\n  --font-size-test-notice: 14px;\n  --font-size-input: 14px;\n  --font-size-header: 20px;\n  --font-size-paragraph: 14px;\n  --font-size-link: 14px;\n  --font-size-error: 12px;\n  --font-size-html-h1: 24px;\n  --font-size-html-h2: 20px;\n  --font-size-html-h3: 16px;\n  --font-size-html-h4: 14px;\n  --font-size-html-h5: 12px;\n  --font-size-html-h6: 10px;\n  --font-size-subheader: 14px;\n\n\t/* Colors */\n  --color-background: #FFFFFF;\n  --color-test-notice-text: #1EAEDB;\n  --color-test-notice-bg: #f0f9ff;\n  --color-test-notice-border: #bae6fd;\n  --color-card-bg: #FFFFFF;\n  --color-card-border: #e2e8f0;\n  --color-card-shadow: rgba(30, 174, 219, 0.06);\n  --color-link: #8E9196;\n  --color-header: #333333;\n  --color-label: #555555;\n  --color-input-border: #e2e8f0;\n  --color-input-text: #4a5568;\n  --color-focus-border: #1EAEDB;\n  --color-submit-btn-bg: #1EAEDB;\n  --color-submit-btn-text: #FFFFFF;\n  --color-error: #ef4444;\n  --color-required: #1EAEDB;\n  --color-clear-button-bg: #8E9196;\n  --color-html-text: #555555;\n  --color-html-link: #1EAEDB;\n  --color-header-subtext: #8E9196;\n\n\t/* Border Radii */\n  --border-radius-card: 0.75rem;\n  --border-radius-input: 0.5rem;\n  --border-radius-clear-btn: 50%;\n  --card-border-radius: 0.75rem;\n\n\t/* Spacing */\n  --padding-container-top: 0px;\n  --padding-card: 24px;\n  --padding-test-notice-vertical: 12px;\n  --padding-test-notice-horizontal: 24px;\n  --margin-bottom-card: 16px;\n  --padding-form-input: 12px;\n  --card-padding: 24px;\n  --card-margin-bottom: 16px;\n\n\t/* Dimensions */\n  --container-width: 100%;\n  --submit-btn-height: 48px;\n  --checkbox-size: 18px;\n\n\t/* Others */\n  --box-shadow-card: 0px 4px 16px 0px rgba(30, 174, 219, 0.06);\n  --opacity-placeholder: 0.5;\n}"}},"type":"n8n-nodes-base.formTrigger","typeVersion":2.2,"position":[-448,192],"id":"d852f498-9501-41fe-b55e-b9122d12e8ea","name":"On form submission","webhookId":"42ab0f49-d386-47ab-858e-06092d014d6a"},{"parameters":{"assignments":{"assignments":[{"id":"f8ef1675-c977-40f8-8fb4-dadee795cb29","name":"instancia","value":"reservas","type":"string"},{"id":"8559cd56-0b64-457c-bc46-d5fcbbd3f41f","name":"contacto","value":"51952373850@s.whatsapp.net","type":"string"},{"id":"42d679b6-2948-4ef2-b996-a60830371fd3","name":"Nombre","value":"={{ $json.Nombre }}","type":"string"},{"id":"e8d44edc-1120-4d02-a5b8-6f25ecd96287","name":"Tel茅fono","value":"={{ $json[\"Tel茅fono\"] }}","type":"string"},{"id":"b8e62bb2-cd11-4829-9c51-7ca584d52941","name":"Correo electr贸nico","value":"={{ $json[\"Correo electr贸nico\"] }}","type":"string"},{"id":"b5b0d955-27ec-4c90-bbce-53304bf0bd78","name":"Mensaje","value":"={{ $json.Mensaje }}","type":"string"}]},"includeOtherFields":true,"options":{}},"type":"n8n-nodes-base.set","typeVersion":3.4,"position":[-224,192],"id":"d98f8489-91fa-4d77-9248-0fb45a74878a","name":"setear"},{"parameters":{"fromEmail":"sender@heleo.com.pe","toEmail":"jesus@heleo.com.pe","subject":"Contacto desde web de eficiencia Cloud","html":"={{ $json.html }}","options":{"appendAttribution":false}},"type":"n8n-nodes-base.emailSend","typeVersion":2.1,"position":[320,192],"id":"e4e281bd-308e-46ba-bdca-c7e4a744866c","name":"Send email","webhookId":"1c84ddb4-964d-423c-aa06-89c048472a08","credentials":{"smtp":{"id":"k3JRkY41OWD5lbru","name":"enviador de correos de workflows"}}},{"parameters":{"html":"<!DOCTYPE html>\n<html lang=\"es\">\n<head>\n  <meta charset=\"UTF-8\">\n  <style>\n    body {\n      font-family: Arial, sans-serif;\n      background-color: #f8f9fa;\n      color: #333;\n      padding: 20px;\n    }\n    .container {\n      max-width: 600px;\n      margin: auto;\n      background: #ffffff;\n      border-radius: 10px;\n      padding: 20px;\n      box-shadow: 0 2px 8px rgba(0,0,0,0.1);\n    }\n    h2 {\n      text-align: center;\n      color: #444;\n    }\n    table {\n      width: 100%;\n      border-collapse: collapse;\n      margin-top: 15px;\n    }\n    th, td {\n      text-align: left;\n      padding: 10px;\n      border-bottom: 1px solid #ddd;\n    }\n    th {\n      background-color: #f1f1f1;\n      color: #555;\n      width: 35%;\n    }\n    td {\n      color: #222;\n    }\n    .footer {\n      margin-top: 20px;\n      text-align: center;\n      font-size: 12px;\n      color: #888;\n    }\n  </style>\n</head>\n<body>\n  <div class=\"container\">\n    <h2> Nuevo Formulario Recibido</h2>\n    <table>\n      <tr>\n        <th>Nombre</th>\n        <td>{{ $json[\"Nombre\"] }}</td>\n      </tr>\n      <tr>\n        <th>Correo electr贸nico</th>\n        <td>{{ $json[\"Correo electr贸nico\"] }}</td>\n      </tr>\n      <tr>\n        <th>Tel茅fono</th>\n        <td>{{ $json[\"Tel茅fono\"] }}</td>\n      </tr>\n      <tr>\n        <th>Mensaje</th>\n        <td>{{ $json[\"Mensaje\"] }}</td>\n      </tr>\n      <tr>\n        <th>Fecha de env铆o</th>\n        <td>{{ $json[\"submittedAt\"] }}</td>\n      </tr>\n      <tr>\n        <th>Instancia</th>\n        <td>{{ $json[\"instancia\"] }}</td>\n      </tr>\n      <tr>\n        <th>Contacto</th>\n        <td>{{ $json[\"contacto\"].replace(\"@s.whatsapp.net\",\"\") }}</td>\n      </tr>\n    </table>\n    <div class=\"footer\">\n      Este mensaje fue generado autom谩ticamente por el flujo de <b>n8n</b>.\n    </div>\n  </div>\n</body>\n</html>\n"},"type":"n8n-nodes-base.html","typeVersion":1.2,"position":[32,192],"id":"42a94256-e621-4a36-9ff8-f2b57a08c936","name":"HTML"}],"connections":{"On form submission":{"main":[[{"node":"setear","type":"main","index":0}]]},"setear":{"main":[[{"node":"HTML","type":"main","index":0}]]},"HTML":{"main":[[{"node":"Send email","type":"main","index":0}]]}},"settings":{"executionOrder":"v1"},"staticData":null,"meta":{"templateCredsSetupCompleted":true},"pinData":{"On form submission":[{"json":{"Nombre":"domingo dias","Correo electr贸nico":"dfdsf@dfsfs.com","Tel茅fono":"945646334","Mensaje":"este es otro mensaje de prueba para ver si funciona el formulario","submittedAt":"2025-04-11T14:16:03.394-05:00","formMode":"production"}}]},"versionId":"c5b490c5-8450-49b2-be64-aae25adae5ed","triggerCount":1,"shared":[{"createdAt":"2025-09-02T21:55:02.315Z","updatedAt":"2025-09-02T21:55:02.315Z","role":"workflow:owner","workflowId":"n2dl4AfPiyRCVxpr","projectId":"SqMi70IbghSQH4eu"}],"tags":[]}